{
  "timestamp": "2025-07-29T00:29:33.304431+00:00",
  "total_files": 56,
  "total_defined_vars": 422,
  "files_with_issues": [
    "tailwind-base.css",
    "footer-clean.css",
    "accessibility-consolidated.css",
    "search-clean.css",
    "onboarding-page.css",
    "garden-ui-core.css",
    "garden-ui-public.css",
    "process-page.css",
    "garden-ui-responsive.css",
    "theme-overrides-clean.css",
    "garden-ui-navigation.css",
    "tailwind-complete.css",
    "garden-ui-tokens.css",
    "tailwind-simple.css",
    "header-text-clean.css",
    "garden-layout-system.css",
    "blog-components-consolidated.css",
    "mobile-consolidated.css",
    "garden-buttons-enhanced.css",
    "garden-ui-header.css",
    "16-homepage-clean.css",
    "login-dropdown-clean.css",
    "garden-ui-footer.css",
    "tailwind.min.css",
    "combined.css",
    "tailwind.css",
    "development.css",
    "garden-ui-core.css",
    "garden-ui-foundation.css",
    "garden-ui-complete.css",
    "garden-ui-layout.css"
  ],
  "undefined_variables": {
    "footer-clean.css": [
      "--garden-footer-link",
      "--z-skip-link",
      "--garden-footer-text",
      "--garden-footer-social-hover-border",
      "--garden-footer-social-bg",
      "--garden-footer-social-hover-icon",
      "--garden-footer-dark-text",
      "--garden-footer-border-light",
      "--garden-footer-dark-link",
      "--garden-footer-dark-heading",
      "--garden-footer-link-hover",
      "--garden-footer-heading",
      "--garden-footer-dark-link-hover",
      "--garden-footer-social-hover-bg",
      "--ease-out",
      "--garden-footer-social-icon",
      "--leading-relaxed",
      "--leading-tight",
      "--garden-footer-social-border"
    ],
    "accessibility-consolidated.css": [
      "--color-error-alpha-5"
    ],
    "search-clean.css": [
      "--color-warning-dark",
      "--color-input-placeholder",
      "--color-input-text",
      "--color-input-dark-bg",
      "--color-input-focus-ring",
      "--color-warning-light",
      "--color-input-bg",
      "--color-input-dark-text",
      "--color-input-border",
      "--ease-out",
      "--color-input-dark-border",
      "--color-input-focus-border",
      "--leading-normal",
      "--color-input-focus-bg"
    ],
    "onboarding-page.css": [
      "--color-error-alpha-light",
      "--color-text-muted",
      "--color-surface-rgb"
    ],
    "process-page.css": [
      "--color-input-bg",
      "--color-input-border"
    ],
    "garden-ui-responsive.css": [
      "--z-overlay"
    ],
    "garden-ui-navigation.css": [
      "--color-warning-dark",
      "--leading-relaxed",
      "--color-input-placeholder",
      "--leading-tight",
      "--color-input-text",
      "--color-input-dark-bg",
      "--color-input-focus-ring",
      "--color-input-dark-border",
      "--color-warning-light",
      "--color-input-bg",
      "--color-input-dark-text",
      "--color-input-border",
      "--ease-out",
      "--color-primary-subtle",
      "--color-input-focus-border",
      "--leading-normal",
      "--color-input-focus-bg"
    ],
    "tailwind-complete.css": [
      "--ec-gray-400",
      "--ec-gray-600",
      "--ec-gray-900",
      "--ec-gray-50",
      "--ec-gray-100",
      "--ec-teal-primary",
      "--ec-gray-700",
      "--ec-gray-200",
      "--ec-gray-500",
      "--ec-teal-dark",
      "--ec-purple-primary",
      "--ec-gray-300",
      "--ec-gray-800"
    ],
    "header-text-clean.css": [
      "--garden-header-bg",
      "--garden-search-bg",
      "--garden-header-text",
      "--garden-header-link",
      "--ease-out",
      "--garden-search-placeholder",
      "--garden-search-text",
      "--garden-search-border"
    ],
    "garden-layout-system.css": [
      "--font-4xl"
    ],
    "blog-components-consolidated.css": [
      "--font-4xl"
    ],
    "mobile-consolidated.css": [
      "--z-overlay"
    ],
    "garden-buttons-enhanced.css": [
      "--ease-out"
    ],
    "garden-ui-header.css": [
      "--garden-header-bg",
      "--garden-search-bg",
      "--garden-header-text",
      "--garden-header-link",
      "--ease-out",
      "--garden-search-placeholder",
      "--garden-search-text",
      "--garden-search-border"
    ],
    "16-homepage-clean.css": [
      "--ease-out"
    ],
    "login-dropdown-clean.css": [
      "--leading-relaxed",
      "--color-primary-subtle",
      "--color-input-border",
      "--leading-tight"
    ],
    "garden-ui-footer.css": [
      "--garden-footer-link",
      "--z-skip-link",
      "--garden-footer-text",
      "--garden-footer-social-hover-border",
      "--garden-footer-social-bg",
      "--garden-footer-social-hover-icon",
      "--garden-footer-dark-text",
      "--garden-footer-border-light",
      "--garden-footer-dark-link",
      "--garden-footer-dark-heading",
      "--garden-footer-link-hover",
      "--garden-footer-heading",
      "--garden-footer-dark-link-hover",
      "--garden-footer-social-hover-bg",
      "--ease-out",
      "--garden-footer-social-icon",
      "--leading-relaxed",
      "--leading-tight",
      "--garden-footer-social-border"
    ],
    "tailwind.min.css": [
      "--tw-space-x-reverse",
      "--default-transition-timing-function",
      "--tw-duration",
      "--color-teal-400",
      "--tw-outline-style",
      "--tw-sepia",
      "--color-teal-900",
      "--tw-leading",
      "--container-3xl",
      "--tw-scale-x",
      "--default-transition-duration",
      "--tw-shadow",
      "--color-red-400",
      "--color-gray-300",
      "--default-mono-font-variation-settings",
      "--default-font-family",
      "--text-sm--line-height",
      "--tw-skew-x",
      "--tw-translate-x",
      "--color-teal-200",
      "--tw-scale-y",
      "--color-white",
      "--color-gray-500",
      "--leading-relaxed",
      "--tw-brightness",
      "--tw-ease",
      "--tw-hue-rotate",
      "--spacing",
      "--color-purple-900",
      "--text-xs--line-height",
      "--container-4xl",
      "--color-red-900",
      "--aspect-video",
      "--tw-rotate-z",
      "--tw-blur",
      "--default-mono-font-family",
      "--tw-border-style",
      "--tw-shadow-color",
      "--text-4xl--line-height",
      "--text-lg--line-height",
      "--ease-in",
      "--tw-translate-y",
      "--color-black",
      "--color-purple-600",
      "--tw-rotate-y",
      "--tw-inset-shadow",
      "--animate-spin",
      "--tw-inset-ring-shadow",
      "--tw-grayscale",
      "--font-weight-semibold",
      "--tw-contrast",
      "--text-3xl--line-height",
      "--color-gray-800",
      "--color-purple-300",
      "--text-5xl",
      "--tw-ring-offset-width",
      "--tracking-wider",
      "--tw-space-y-reverse",
      "--tw-ring-inset",
      "--default-mono-font-feature-settings",
      "--default-font-variation-settings",
      "--color-green-200",
      "--color-green-900",
      "--ease-out",
      "--tw-skew-y",
      "--color-gray-700",
      "--font-weight-medium",
      "--text-5xl--line-height",
      "--tw-invert",
      "--leading-tight",
      "--color-red-200",
      "--font-weight-bold",
      "--tw-rotate-x",
      "--default-font-feature-settings",
      "--tw-drop-shadow",
      "--tw-ring-offset-shadow",
      "--text-xl--line-height",
      "--color-yellow-900",
      "--color-gray-200",
      "--tw-saturate",
      "--color-purple-400",
      "--color-purple-800",
      "--tw-ring-shadow",
      "--color-gray-100",
      "--color-gray-600",
      "--tw-ring-color",
      "--text-2xl--line-height",
      "--color-gray-900",
      "--color-purple-200",
      "--color-purple-700",
      "--color-gray-400",
      "--color-yellow-200"
    ],
    "combined.css": [
      "--garden-header-bg",
      "--color-surface-rgb",
      "--garden-footer-link",
      "--color-warning-light",
      "--color-input-bg",
      "--garden-header-link",
      "--z-skip-link",
      "--garden-footer-text",
      "--color-input-text",
      "--color-input-dark-bg",
      "--garden-search-bg",
      "--garden-footer-social-hover-border",
      "--garden-footer-social-bg",
      "--garden-footer-social-hover-icon",
      "--garden-footer-dark-text",
      "--garden-footer-border-light",
      "--color-error-alpha-light",
      "--garden-footer-dark-link",
      "--garden-search-text",
      "--leading-normal",
      "--color-warning-dark",
      "--garden-footer-dark-heading",
      "--garden-footer-link-hover",
      "--garden-footer-heading",
      "--color-input-focus-ring",
      "--garden-footer-dark-link-hover",
      "--color-input-border",
      "--z-overlay",
      "--garden-footer-social-hover-bg",
      "--ease-out",
      "--garden-footer-social-icon",
      "--color-input-dark-border",
      "--color-primary-subtle",
      "--garden-search-border",
      "--color-input-focus-bg",
      "--garden-search-placeholder",
      "--leading-relaxed",
      "--font-4xl",
      "--color-input-placeholder",
      "--leading-tight",
      "--garden-footer-social-border",
      "--garden-header-text",
      "--color-error-alpha-5",
      "--color-text-muted",
      "--color-input-focus-border",
      "--color-input-dark-text"
    ],
    "tailwind.css": [
      "--tw-space-x-reverse",
      "--text-7xl--line-height",
      "--default-transition-timing-function",
      "--color-green-300",
      "--text-6xl",
      "--tw-duration",
      "--color-blue-800",
      "--font-weight-normal",
      "--color-blue-200",
      "--tw-gradient-from",
      "--color-teal-400",
      "--color-green-50",
      "--tw-outline-style",
      "--tw-sepia",
      "--color-teal-900",
      "--tw-leading",
      "--container-3xl",
      "--tw-scale-x",
      "--default-transition-duration",
      "--color-orange-600",
      "--color-orange-500",
      "--font-weight-light",
      "--tw-shadow",
      "--color-red-400",
      "--color-orange-700",
      "--color-gray-50",
      "--tw-backdrop-contrast",
      "--color-gray-300",
      "--default-mono-font-variation-settings",
      "--default-font-family",
      "--color-purple-500",
      "--text-sm--line-height",
      "--tw-skew-x",
      "--color-slate-600",
      "--tw-translate-x",
      "--color-teal-200",
      "--tw-scale-y",
      "--color-white",
      "--color-gray-500",
      "--leading-relaxed",
      "--tw-brightness",
      "--color-yellow-500",
      "--tw-hue-rotate",
      "--color-red-600",
      "--tw-ease",
      "--color-slate-100",
      "--spacing",
      "--color-purple-900",
      "--container-4xl",
      "--text-xs--line-height",
      "--tw-border-spacing-y",
      "--tracking-tighter",
      "--color-red-900",
      "--aspect-video",
      "--tw-rotate-z",
      "--color-red-300",
      "--default-mono-font-family",
      "--tw-blur",
      "--color-orange-50",
      "--tw-border-style",
      "--tw-shadow-color",
      "--color-red-500",
      "--text-4xl--line-height",
      "--tw-gradient-stops",
      "--text-lg--line-height",
      "--color-blue-500",
      "--ease-in",
      "--tw-gradient-via-stops",
      "--tw-translate-y",
      "--tracking-widest",
      "--color-yellow-100",
      "--tw-gradient-via-position",
      "--color-black",
      "--color-purple-50",
      "--tw-backdrop-sepia",
      "--color-slate-700",
      "--tw-gradient-via",
      "--color-purple-600",
      "--color-blue-50",
      "--tw-rotate-y",
      "--tw-inset-shadow",
      "--animate-spin",
      "--color-slate-900",
      "--color-green-400",
      "--color-orange-300",
      "--tw-gradient-to",
      "--color-slate-200",
      "--tw-inset-ring-shadow",
      "--tw-shadow-alpha",
      "--text-base--line-height",
      "--color-teal-50",
      "--tw-grayscale",
      "--font-weight-semibold",
      "--blur-sm",
      "--tw-contrast",
      "--color-teal-600",
      "--tracking-tight",
      "--text-3xl--line-height",
      "--text-7xl",
      "--color-yellow-800",
      "--color-blue-400",
      "--color-red-50",
      "--color-gray-800",
      "--tw-gradient-position",
      "--color-purple-300",
      "--text-5xl",
      "--text-6xl--line-height",
      "--tracking-wider",
      "--tw-ring-offset-width",
      "--tw-space-y-reverse",
      "--tw-ring-inset",
      "--color-blue-900",
      "--default-mono-font-feature-settings",
      "--default-font-variation-settings",
      "--color-red-700",
      "--color-green-200",
      "--tw-border-spacing-x",
      "--color-green-900",
      "--tw-backdrop-blur",
      "--color-blue-700",
      "--ease-out",
      "--tw-skew-y",
      "--color-gray-700",
      "--text-5xl--line-height",
      "--font-weight-medium",
      "--tw-invert",
      "--leading-tight",
      "--color-red-200",
      "--color-blue-600",
      "--font-weight-bold",
      "--color-green-100",
      "--tw-backdrop-saturate",
      "--color-blue-100",
      "--color-green-600",
      "--color-teal-300",
      "--tw-backdrop-invert",
      "--color-green-500",
      "--text-8xl",
      "--tw-rotate-x",
      "--text-8xl--line-height",
      "--color-yellow-50",
      "--default-font-feature-settings",
      "--color-blue-300",
      "--tw-drop-shadow",
      "--tw-ring-offset-shadow",
      "--color-purple-100",
      "--color-green-800",
      "--text-xl--line-height",
      "--color-red-100",
      "--color-yellow-900",
      "--color-orange-900",
      "--tw-gradient-to-position",
      "--color-gray-200",
      "--tw-saturate",
      "--tw-backdrop-grayscale",
      "--color-purple-400",
      "--color-purple-800",
      "--tw-ring-shadow",
      "--color-gray-100",
      "--color-slate-300",
      "--tw-backdrop-brightness",
      "--color-orange-800",
      "--color-slate-800",
      "--color-gray-600",
      "--tw-ring-color",
      "--tw-gradient-from-position",
      "--tracking-wide",
      "--color-green-700",
      "--text-2xl--line-height",
      "--color-gray-900",
      "--color-purple-200",
      "--color-red-800",
      "--tw-backdrop-opacity",
      "--color-orange-200",
      "--color-purple-700",
      "--tw-backdrop-hue-rotate",
      "--color-gray-400",
      "--color-yellow-200"
    ],
    "development.css": [
      "--garden-header-bg",
      "--color-surface-rgb",
      "--garden-footer-link",
      "--color-warning-light",
      "--color-input-bg",
      "--garden-header-link",
      "--z-skip-link",
      "--garden-footer-text",
      "--color-input-text",
      "--color-input-dark-bg",
      "--garden-search-bg",
      "--garden-footer-social-hover-border",
      "--garden-footer-social-bg",
      "--garden-footer-social-hover-icon",
      "--garden-footer-dark-text",
      "--garden-footer-border-light",
      "--color-error-alpha-light",
      "--garden-footer-dark-link",
      "--garden-search-text",
      "--leading-normal",
      "--color-warning-dark",
      "--garden-footer-dark-heading",
      "--garden-footer-link-hover",
      "--garden-footer-heading",
      "--color-input-focus-ring",
      "--garden-footer-dark-link-hover",
      "--color-input-border",
      "--z-overlay",
      "--garden-footer-social-hover-bg",
      "--ease-out",
      "--garden-footer-social-icon",
      "--color-input-dark-border",
      "--color-primary-subtle",
      "--garden-search-border",
      "--color-input-focus-bg",
      "--garden-search-placeholder",
      "--leading-relaxed",
      "--font-4xl",
      "--color-input-placeholder",
      "--leading-tight",
      "--garden-footer-social-border",
      "--garden-header-text",
      "--color-error-alpha-5",
      "--color-text-muted",
      "--color-input-focus-border",
      "--color-input-dark-text"
    ],
    "garden-ui-complete.css": [
      "--garden-header-bg",
      "--garden-footer-link",
      "--color-warning-light",
      "--color-input-bg",
      "--garden-header-link",
      "--z-skip-link",
      "--garden-footer-text",
      "--color-input-text",
      "--garden-search-bg",
      "--color-input-dark-bg",
      "--garden-footer-social-hover-border",
      "--garden-footer-social-bg",
      "--garden-footer-social-hover-icon",
      "--garden-footer-dark-text",
      "--garden-footer-border-light",
      "--garden-footer-dark-link",
      "--garden-search-text",
      "--leading-normal",
      "--color-warning-dark",
      "--garden-footer-dark-heading",
      "--garden-footer-link-hover",
      "--color-input-focus-ring",
      "--garden-footer-heading",
      "--garden-footer-dark-link-hover",
      "--z-overlay",
      "--color-input-border",
      "--ease-out",
      "--color-primary-subtle",
      "--garden-search-placeholder",
      "--color-input-dark-border",
      "--garden-footer-social-icon",
      "--garden-search-border",
      "--color-input-focus-bg",
      "--garden-footer-social-hover-bg",
      "--leading-relaxed",
      "--color-input-placeholder",
      "--leading-tight",
      "--garden-footer-social-border",
      "--garden-header-text",
      "--color-input-focus-border",
      "--color-input-dark-text"
    ],
    "garden-ui-layout.css": [
      "--garden-header-bg",
      "--garden-footer-link",
      "--color-warning-light",
      "--color-input-bg",
      "--garden-header-link",
      "--z-skip-link",
      "--garden-footer-text",
      "--color-input-text",
      "--garden-search-bg",
      "--color-input-dark-bg",
      "--garden-footer-social-hover-border",
      "--garden-footer-social-bg",
      "--garden-footer-social-hover-icon",
      "--garden-footer-dark-text",
      "--garden-footer-border-light",
      "--garden-footer-dark-link",
      "--garden-search-text",
      "--leading-normal",
      "--color-warning-dark",
      "--garden-footer-dark-heading",
      "--garden-footer-link-hover",
      "--color-input-focus-ring",
      "--garden-footer-heading",
      "--garden-footer-dark-link-hover",
      "--z-overlay",
      "--color-input-border",
      "--ease-out",
      "--color-primary-subtle",
      "--garden-search-placeholder",
      "--color-input-dark-border",
      "--garden-footer-social-icon",
      "--garden-search-border",
      "--color-input-focus-bg",
      "--garden-footer-social-hover-bg",
      "--leading-relaxed",
      "--color-input-placeholder",
      "--leading-tight",
      "--garden-footer-social-border",
      "--garden-header-text",
      "--color-input-focus-border",
      "--color-input-dark-text"
    ]
  },
  "hardcoded_colors": {
    "tailwind-base.css": [
      [
        6,
        "#1a1a1a"
      ],
      [
        7,
        "#4a5568"
      ],
      [
        8,
        "#718096"
      ],
      [
        9,
        "#ffffff"
      ],
      [
        10,
        "#f7fafc"
      ]
    ],
    "footer-clean.css": [
      [
        44,
        "#fcefef"
      ],
      [
        45,
        "#b57edc"
      ],
      [
        51,
        "#333"
      ],
      [
        275,
        "#1a1a1a"
      ],
      [
        276,
        "#3d2970"
      ]
    ],
    "garden-ui-core.css": [
      [
        1763,
        "#fff"
      ],
      [
        2286,
        "#fff"
      ],
      [
        2916,
        "#553C9A"
      ],
      [
        2918,
        "#553C9A"
      ],
      [
        2922,
        "#553C9A"
      ]
    ],
    "garden-ui-public.css": [
      [
        57,
        "#dcfce7"
      ],
      [
        58,
        "#bbf7d0"
      ],
      [
        59,
        "#86efac"
      ],
      [
        60,
        "#22c55e"
      ],
      [
        61,
        "#34d399"
      ]
    ],
    "garden-ui-theme.css": [
      [
        54,
        "#dcfce7"
      ],
      [
        55,
        "#bbf7d0"
      ],
      [
        56,
        "#86efac"
      ],
      [
        57,
        "#22c55e"
      ],
      [
        58,
        "#34d399"
      ]
    ],
    "theme-overrides-clean.css": [
      [
        11,
        "#fcefef"
      ],
      [
        16,
        "#111"
      ],
      [
        23,
        "#b57edc"
      ],
      [
        32,
        "#2d7a68"
      ],
      [
        33,
        "#fff"
      ]
    ],
    "tailwind-complete.css": [
      [
        67,
        "#553c9a"
      ],
      [
        79,
        "#c4b5fd"
      ],
      [
        168,
        "#a855f7"
      ],
      [
        364,
        "#f9fafb"
      ],
      [
        365,
        "#f3f4f6"
      ]
    ],
    "garden-ui-tokens.css": [
      [
        56,
        "#dcfce7"
      ],
      [
        57,
        "#bbf7d0"
      ],
      [
        58,
        "#86efac"
      ],
      [
        59,
        "#22c55e"
      ],
      [
        60,
        "#34d399"
      ]
    ],
    "tailwind-simple.css": [
      [
        6,
        "#1a1a1a"
      ],
      [
        7,
        "#4a5568"
      ],
      [
        8,
        "#718096"
      ],
      [
        9,
        "#fff"
      ],
      [
        10,
        "#f7fafc"
      ]
    ],
    "garden-buttons-enhanced.css": [
      [
        278,
        "#9d7bda"
      ]
    ],
    "garden-ui-layout.css": [
      [
        1460,
        "#FCEFEF"
      ],
      [
        1461,
        "#B57EDC"
      ],
      [
        1621,
        "#1a1a1a"
      ],
      [
        1622,
        "#3d2970"
      ]
    ],
    "garden-ui-footer.css": [
      [
        47,
        "#fcefef"
      ],
      [
        48,
        "#b57edc"
      ],
      [
        234,
        "#1a1a1a"
      ],
      [
        235,
        "#3d2970"
      ]
    ],
    "tailwind.min.css": [
      [
        1,
        "#0000"
      ],
      [
        1,
        "#0000"
      ],
      [
        1,
        "#0000"
      ],
      [
        1,
        "#0000"
      ],
      [
        1,
        "#fff"
      ]
    ],
    "combined.css": [
      [
        59,
        "#dcfce7"
      ],
      [
        60,
        "#bbf7d0"
      ],
      [
        61,
        "#86efac"
      ],
      [
        62,
        "#22c55e"
      ],
      [
        63,
        "#34d399"
      ]
    ],
    "tailwind.css": [
      [
        87,
        "#000"
      ],
      [
        88,
        "#fff"
      ],
      [
        1166,
        "#fff"
      ],
      [
        1170,
        "#fff"
      ],
      [
        1174,
        "#fff"
      ]
    ],
    "development.css": [
      [
        59,
        "#dcfce7"
      ],
      [
        60,
        "#bbf7d0"
      ],
      [
        61,
        "#86efac"
      ],
      [
        62,
        "#22c55e"
      ],
      [
        63,
        "#34d399"
      ]
    ],
    "garden-ui-foundation.css": [
      [
        100,
        "#dcfce7"
      ],
      [
        101,
        "#bbf7d0"
      ],
      [
        102,
        "#86efac"
      ],
      [
        103,
        "#22c55e"
      ],
      [
        104,
        "#34d399"
      ]
    ],
    "garden-ui-complete.css": [
      [
        110,
        "#dcfce7"
      ],
      [
        111,
        "#bbf7d0"
      ],
      [
        112,
        "#86efac"
      ],
      [
        113,
        "#22c55e"
      ],
      [
        114,
        "#34d399"
      ]
    ]
  },
  "file_sizes": {
    "tailwind-base.css": 6.27,
    "responsive-utilities-layered.css": 2.99,
    "garden-ui-panels.css": 7.0,
    "footer-clean.css": 7.92,
    "accessibility-consolidated.css": 6.91,
    "search-clean.css": 8.23,
    "onboarding-page.css": 24.87,
    "garden-ui-core.css": 104.09,
    "garden-ui-public.css": 122.28,
    "header-layout-layers.css": 3.27,
    "garden-ui-theme.css": 205.32,
    "pricing-features-fix.css": 0.7,
    "contact-page-fixes.css": 6.39,
    "process-page.css": 16.8,
    "garden-ui-layers.css": 0.86,
    "garden-data-table.css": 9.95,
    "core-styles.css": 17.42,
    "garden-ui-responsive.css": 15.27,
    "blog-consistency-consolidated.css": 6.77,
    "theme-overrides-clean.css": 3.05,
    "responsive-breakpoints-fix.css": 5.65,
    "garden-ui-navigation.css": 14.59,
    "blog-core-consolidated.css": 6.97,
    "tailwind-complete.css": 15.01,
    "garden-ui-tokens.css": 35.05,
    "tailwind-simple.css": 2.35,
    "header-text-clean.css": 4.39,
    "garden-ui-buttons.css": 19.43,
    "garden-layout-system.css": 11.54,
    "faq-page-fixes.css": 5.09,
    "blog-components-consolidated.css": 8.53,
    "garden-ui-forms.css": 5.39,
    "mobile-consolidated.css": 6.15,
    "about-page-v2.css": 7.37,
    "tailwind-minimal.css": 0.0,
    "responsive-layout-system.css": 5.76,
    "garden-widgets.css": 6.36,
    "garden-buttons-enhanced.css": 8.97,
    "garden-ui-typography.css": 2.65,
    "garden-ui-advanced-layers.css": 1.42,
    "garden-ui-header.css": 7.47,
    "16-homepage-clean.css": 14.56,
    "login-dropdown-clean.css": 6.61,
    "cta-tiffany-blue.css": 2.84,
    "garden-ui-layout.css": 35.02,
    "garden-ui-footer.css": 8.12,
    "strategy-right-rail-buttons.css": 4.04,
    "tailwind.min.css": 51.14,
    "combined.css": 1055.73,
    "tailwind.css": 128.8,
    "development.css": 1055.73,
    "garden-ui-foundation.css": 29.44,
    "garden-ui-complete.css": 167.89
  },
  "total_undefined_vars": 558,
  "is_baseline": true,
  "baseline_created": "2025-07-29T00:29:33.401189+00:00"
}
